GenshinHarpPC/GenshinHarp.py
GenshinHarpPC/__init__.py
GenshinHarpPC-0.0.4.dist-info/LICENSE
GenshinHarpPC-0.0.4.dist-info/METADATA
GenshinHarpPC-0.0.4.dist-info/WHEEL
GenshinHarpPC-0.0.4.dist-info/top_level.txt
GenshinHarpPC-0.0.4.dist-info/RECORD
